Metadata-Version: 1.0
Name: probability-dstbn
Version: 1.11
Summary: Gaussian and Binomial distribution simplified
Home-page: UNKNOWN
Author: Pratik Poudel
Author-email: xpresspratik@gmail.com
License: UNKNOWN
Platform: UNKNOWN
